odoo/addons/agreement_stock/README.rst
odoo/addons/agreement_stock/__init__.py
odoo/addons/agreement_stock/__manifest__.py
odoo/addons/agreement_stock/i18n/agreement_stock.pot
odoo/addons/agreement_stock/i18n/de.po
odoo/addons/agreement_stock/models/__init__.py
odoo/addons/agreement_stock/models/agreement.py
odoo/addons/agreement_stock/models/stock.py
odoo/addons/agreement_stock/readme/CONTRIBUTORS.rst
odoo/addons/agreement_stock/readme/CREDITS.rst
odoo/addons/agreement_stock/readme/DESCRIPTION.rst
odoo/addons/agreement_stock/readme/ROADMAP.rst
odoo/addons/agreement_stock/readme/USAGE.rst
odoo/addons/agreement_stock/static/description/icon.png
odoo/addons/agreement_stock/static/description/index.html
odoo/addons/agreement_stock/views/agreement_view.xml
odoo/addons/agreement_stock/views/stock_view.xml
odoo11_addon_agreement_stock-11.0.0.0.1.99.dev8.dist-info/METADATA
odoo11_addon_agreement_stock-11.0.0.0.1.99.dev8.dist-info/WHEEL
odoo11_addon_agreement_stock-11.0.0.0.1.99.dev8.dist-info/top_level.txt
odoo11_addon_agreement_stock-11.0.0.0.1.99.dev8.dist-info/RECORD
